ctrlf/__init__.py
ctrlf/api.py
ctrlf_python-0.1.2.dist-info/LICENSE
ctrlf_python-0.1.2.dist-info/METADATA
ctrlf_python-0.1.2.dist-info/WHEEL
ctrlf_python-0.1.2.dist-info/top_level.txt
ctrlf_python-0.1.2.dist-info/RECORD
